bcdict/__init__.py
bcdict/bcdict.py
bcdict-0.5.0.dist-info/LICENSE
bcdict-0.5.0.dist-info/WHEEL
bcdict-0.5.0.dist-info/METADATA
bcdict-0.5.0.dist-info/RECORD
