Metadata-Version: 2.1
Name: bcdict
Version: 0.5.0
Summary: Python dictionary with broadcast support.
Home-page: https://github.com/mariushelf/bcdict
License: MIT
Author: Marius Helf
Author-email: marius@happyyeti.tech
Requires-Python: >=3.7.1,<4.0.0
Classifier: Development Status :: 4 - Beta
Classifier: License :: OSI Approved :: MIT License
Classifier: Programming Language :: Python :: 3
Classifier: Programming Language :: Python :: 3.10
Classifier: Programming Language :: Python :: 3.7
Classifier: Programming Language :: Python :: 3.8
Classifier: Programming Language :: Python :: 3.9
Classifier: Programming Language :: Python :: Implementation :: PyPy
Provides-Extra: docs
Requires-Dist: Sphinx (>=4.5.0,<5.0.0); extra == "docs"
Requires-Dist: importlib-metadata (>=4.11.3,<5.0.0); python_version < "3.8"
Requires-Dist: myst-nb (>=0.13.2,<0.14.0); extra == "docs"
Requires-Dist: pandas (==1.3.1); (python_version < "3.10" and implementation_name == "cpython") and (extra == "docs")
Requires-Dist: scikit-learn (==1.0.2); (python_version < "3.10" and implementation_name == "cpython") and (extra == "docs")
Requires-Dist: sphinx-autobuild (>=2021.3.14,<2022.0.0); extra == "docs"
Requires-Dist: sphinx-book-theme (>=0.3.2,<0.4.0); extra == "docs"
Requires-Dist: sphinx-copybutton (>=0.5.0,<0.6.0); extra == "docs"
Requires-Dist: sphinx-panels (>=0.6.0,<0.7.0); extra == "docs"
Requires-Dist: sphinxcontrib-mermaid (>=0.7.1,<0.8.0); extra == "docs"
Project-URL: Documentation, https://bcdict.readthedocs.io
Project-URL: Repository, https://github.com/mariushelf/bcdict
